delta/__init__.py
delta/_conversions.py
delta/_version.py
delta/assets.py
delta/cli.py
delta/config.py
delta/data.py
delta/imgops.py
delta/lineage.py
delta/model.py
delta/pipeline.py
delta/utils.py
delta_microscopy-3.0.0a6.dist-info/METADATA
delta_microscopy-3.0.0a6.dist-info/WHEEL
delta_microscopy-3.0.0a6.dist-info/entry_points.txt
delta_microscopy-3.0.0a6.dist-info/licenses/LICENSE
delta_microscopy-3.0.0a6.dist-info/RECORD
